MANIFEST.in
setup.py
bin/start_shopify_app
django_shopify.egg-info/PKG-INFO
django_shopify.egg-info/SOURCES.txt
django_shopify.egg-info/dependency_links.txt
django_shopify.egg-info/requires.txt
django_shopify.egg-info/top_level.txt
shopify_app/__init__.py
shopify_app/admin.py
shopify_app/config.py
shopify_app/decorators.py
shopify_app/models.py
shopify_app/urls.py
shopify_app/management/__init__.py
shopify_app/management/commands/__init__.py
shopify_app/management/commands/start_shopify_app.py
shopify_app/management/commands/lib/__init__.py
shopify_app/management/commands/lib/ansicolors.py
shopify_app/management/commands/lib/builder.py
shopify_app/management/commands/lib/templates.py
shopify_app/management/commands/templates/index.html.tm
shopify_app/management/commands/templates/index.tm
shopify_app/management/commands/templates/login.html.tm
shopify_app/management/commands/templates/settings.tm
shopify_app/management/commands/templates/settings_public.tm
shopify_app/management/commands/templates/urls.tm
shopify_app/management/commands/templates/urls_public.tm
shopify_app/services/__init__.py
shopify_app/services/base.py
shopify_app/services/config_service.py
shopify_app/services/log_service.py
shopify_app/services/plan_config_service.py
shopify_app/services/plan_service.py
shopify_app/services/shop_service.py
shopify_app/services/shopify_api.py
shopify_app/services/shopify_service.py
shopify_app/tests/__init__.py
shopify_app/tests/test_config_service.py
shopify_app/tests/test_django_commands.py
shopify_app/tests/test_oauth_view.py
shopify_app/tests/test_shop_service.py
shopify_app/tests/test_shop_view.py
shopify_app/tests/test_shopify_service.py
shopify_app/utils/__init__.py
shopify_app/utils/email.py
shopify_app/utils/export.py
shopify_app/utils/importer.py
shopify_app/utils/python.py
shopify_app/utils/render.py
shopify_app/views/__init__.py
shopify_app/views/base.py
shopify_app/views/error.py
shopify_app/views/oauth.py
shopify_app/views/shop.py