Metadata-Version: 1.1
Name: django-shopify
Version: 0.4.0
Summary: Django-Shopify generic app
Home-page: https://github.com/SocalProofit/django-shopify
Author: Bootstrap Heroes Developers
Author-email: jmg.utn@gmail.com
License: UNKNOWN
Platform: UNKNOWN
Classifier: Framework :: Django
Classifier: Operating System :: OS Independent
Classifier: Topic :: Software Development
Classifier: Programming Language :: Python :: 2.7
